gcd_processor.v
//-------------------------------------------------------------------//
// Author	: Inc
// Module	: gcd_processor.v
// Date		: June 23
// Version	: v1
// Remarks	: Initial Draft
//
//
// ------------------------------------------------------------------//
`timescale 1 ns/ 1 ns

module gcd_processor #(parameter BIT_LEN = 8) (
  input wire                clk_i  ,
  input wire                reset_n,

  input wire [BIT_LEN-1:0]  num_0  ,
  input wire [BIT_LEN-1:0]  num_1  ,
  input wire                start  ,
 
  output reg                busy   ,
  output wire [BIT_LEN-1:0] gcd_op ,
  output reg                done  
);

localparam IDLE         = 3'd0,
	   PRE_PROCESS  = 3'd1,
	   POST_PROCESS = 3'd2,
	   DONE         = 3'd3;


reg [2:0]         gcd_state_reg;   
reg [2:0]         gcd_state_nxt;

reg [BIT_LEN-1:0] num_0_reg;
reg [BIT_LEN-1:0] num_0_nxt;

reg [BIT_LEN-1:0] num_1_reg;
reg [BIT_LEN-1:0] num_1_nxt;


reg [BIT_LEN-1:0] gcd_op_reg;
reg [BIT_LEN-1:0] gcd_op_nxt;

reg [BIT_LEN-1:0] mult_cntr_reg;
reg [BIT_LEN-1:0] mult_cntr_nxt;

assign gcd_op = gcd_op_reg;



always @(posedge clk_i, negedge reset_n) begin
  if (!reset_n) begin
    gcd_state_reg      <= IDLE;
    num_0_reg          <= 'd0;
    num_1_reg          <= 'd0;
    gcd_op_reg         <= 'd0;
    mult_cntr_reg      <= 'd0;
  end else begin
    gcd_state_reg      <= gcd_state_nxt;
    num_0_reg          <= num_0_nxt;
    num_1_reg          <= num_1_nxt;
    gcd_op_reg         <= gcd_op_nxt;
    mult_cntr_reg      <= mult_cntr_nxt;
  end
end


always @* begin
  gcd_state_nxt = gcd_state_reg;
  num_0_nxt     = num_0_reg;
  num_1_nxt     = num_1_reg;
  gcd_op_nxt    = gcd_op_reg;
  mult_cntr_nxt = mult_cntr_reg;
  done          = 1'b0;
  busy          = 1'b0; 
  case (gcd_state_reg)
    IDLE: begin	    
      if (start) begin
	num_0_nxt       = num_0;      
	num_1_nxt       = num_1;
        busy            = 1'b1;
        mult_cntr_nxt   = 'd0;	
        gcd_state_nxt   = PRE_PROCESS;
        if ((num_0 == 'd0) && (num_1 == 'd0)) begin
          gcd_state_nxt = DONE;
	  gcd_op_nxt    = 'd0; 
        end
        else if (num_0 == 'd0) begin
          gcd_state_nxt = DONE;
	  gcd_op_nxt    = num_1; 
        end		
        else if (num_1 == 'd0) begin
          gcd_state_nxt = DONE;
	  gcd_op_nxt    = num_0; 
        end	
      end	      
    end
    PRE_PROCESS: begin
      busy              = 1'b1;	    
      if (num_0_reg == 'd0) begin
        gcd_state_nxt   = POST_PROCESS;
        gcd_op_nxt      = num_1_reg;	
      end
      else if (num_1_reg == 'd0) begin
        gcd_state_nxt   = POST_PROCESS;
        gcd_op_nxt      = num_0_reg;	
      end      
      else if (~num_0_reg[0] & ~num_1_reg[0]) begin     // Num-0 and NUm-1 are Even
        num_0_nxt      = num_0_reg >> 1;   
        num_1_nxt      = num_1_reg >> 1;  
        mult_cntr_nxt  = mult_cntr_reg + 1'b1;
        gcd_state_nxt  = PRE_PROCESS;	
      end	      
      else if (~num_0_reg[0]) begin                    // Num-0 is Even
        num_0_nxt      = num_0_reg >> 1;   
        gcd_state_nxt  = PRE_PROCESS;	
      end
      else if (~num_1_reg[0]) begin                    // Num-0 is Even
        num_1_nxt      = num_1_reg >> 1;   
        gcd_state_nxt  = PRE_PROCESS;	
      end
      else if (num_0_reg > num_1_reg) begin           // Both are ODD
        num_0_nxt      = (num_0_reg - num_1_reg) >> 1;
        gcd_state_nxt  = PRE_PROCESS;	
      end
      else  begin                                     // Both are Odd
        num_1_nxt      = (num_1_reg - num_0_reg) >> 1;
        gcd_state_nxt  = PRE_PROCESS;	
      end
    end
    POST_PROCESS: begin
      busy            = 1'b1;	    
      if (mult_cntr_reg > 0) begin
        gcd_state_nxt = POST_PROCESS;
	gcd_op_nxt    = gcd_op_reg << 1;
	mult_cntr_nxt = mult_cntr_reg - 1'b1;
      end
      else begin
        gcd_state_nxt  = DONE;	
      end      
    end
    DONE: begin
      done          = 1'b1;
      busy          = 1'b1;      
      gcd_state_nxt = IDLE;
    end    
  endcase	 
end

endmodule

tb_gcd_processor.v
//-------------------------------------------------------------------//
// Author	: Inc
// Module	: tb_gcd_processor.v
// Date		: June 23
// Version	: v1
// Remarks	: Initial Draft
//
//
// ------------------------------------------------------------------//
`timescale 1 ns/ 1 ns

module tb_gcd_processor;
  parameter BIT_LEN = 32 ;
  reg                clk_i   = 0;
  reg                reset_n = 0; 

  reg [BIT_LEN-1:0]  num_0  = 0;
  reg [BIT_LEN-1:0]  num_1  = 0;
  reg                start  = 0;
 
  wire                busy     ;
  wire [BIT_LEN-1:0] gcd_op    ;
  wire               done      ;


gcd_processor #(.BIT_LEN(BIT_LEN) )GCD_PROCESSOR_U1 (
  .clk_i         (clk_i    ),
  .reset_n       (reset_n  ),
  .num_0         (num_0    ),
  .num_1         (num_1    ),
  .start         (start    ),
  .busy          (busy     ),
  .gcd_op        (gcd_op   ),
  .done          (done     )
);

always #10 clk_i = ~ clk_i;

task async_reset_generator; begin
  reset_n = 1'b1;
  #100;
  reset_n = 1'b0;
  #100;
  reset_n = 1'b1;
end
endtask



initial begin
  $dumpfile ("tb_gcd_processor.vcd");
  $dumpvars(0,tb_gcd_processor);
  #100;
  async_reset_generator;
  #100;

  wait (reset_n == 1'b1);
  $display ("De asserted reset");

  num_0 = 'd2;
  num_1 = 'd20261;

  @(negedge clk_i);
  start = 1'b1;  
  @(negedge clk_i);
  start = 1'b0;  

  wait (done);
  $display ("Completed Process...");
  $display ("GCD = %d",gcd_op);
  
  #100;
  $finish;

end








endmodule

tb_gcd_processor.vcd
$date
	Sun Jun 11 14:47:33 2023
$end
$version
	Icarus Verilog
$end
$timescale
	1ns
$end
$scope module tb_gcd_processor $end
$var wire 32 ! gcd_op [31:0] $end
$var wire 1 " done $end
$var wire 1 # busy $end
$var reg 1 $ clk_i $end
$var reg 32 % num_0 [31:0] $end
$var reg 32 & num_1 [31:0] $end
$var reg 1 ' reset_n $end
$var reg 1 ( start $end
$scope module GCD_PROCESSOR_U1 $end
$var wire 1 $ clk_i $end
$var wire 32 ) gcd_op [31:0] $end
$var wire 32 * num_0 [31:0] $end
$var wire 32 + num_1 [31:0] $end
$var wire 1 ' reset_n $end
$var wire 1 ( start $end
$var reg 1 # busy $end
$var reg 1 " done $end
$var reg 32 , gcd_op_nxt [31:0] $end
$var reg 32 - gcd_op_reg [31:0] $end
$var reg 3 . gcd_state_nxt [2:0] $end
$var reg 3 / gcd_state_reg [2:0] $end
$var reg 32 0 mult_cntr_nxt [31:0] $end
$var reg 32 1 mult_cntr_reg [31:0] $end
$var reg 32 2 num_0_nxt [31:0] $end
$var reg 32 3 num_0_reg [31:0] $end
$var reg 32 4 num_1_nxt [31:0] $end
$var reg 32 5 num_1_reg [31:0] $end
$upscope $end
$scope task async_reset_generator $end
$upscope $end
$upscope $end
$enddefinitions $end
#0
$dumpvars
b0 5
b0 4
b0 3
b0 2
b0 1
b0 0
b0 /
b0 .
b0 -
b0 ,
b0 +
b0 *
b0 )
0(
0'
b0 &
b0 %
0$
0#
0"
b0 !
$end
#10
1$
#20
0$
#30
1$
#40
0$
#50
1$
#60
0$
#70
1$
#80
0$
#90
1$
#100
0$
1'
#110
1$
#120
0$
#130
1$
#140
0$
#150
1$
#160
0$
#170
1$
#180
0$
#190
1$
#200
0$
0'
#210
1$
#220
0$
#230
1$
#240
0$
#250
1$
#260
0$
#270
1$
#280
0$
#290
1$
#300
0$
1'
#310
1$
#320
0$
#330
1$
#340
0$
#350
1$
#360
0$
#370
1$
#380
0$
#390
1$
#400
b1 .
1#
b100111100100101 4
b10 2
1(
0$
b100111100100101 &
b100111100100101 +
b10 %
b10 *
#410
b1 2
1#
b100111100100101 5
b10 3
b1 /
1$
#420
1#
b1 2
0(
0$
#430
b10011110010010 4
1#
b1 3
1$
#440
0$
#450
b1001111001001 4
1#
b10011110010010 5
1$
#460
0$
#470
b100111100100 4
1#
b1001111001001 5
1$
#480
0$
#490
b10011110010 4
1#
b100111100100 5
1$
#500
0$
#510
b1001111001 4
1#
b10011110010 5
1$
#520
0$
#530
b100111100 4
1#
b1001111001 5
1$
#540
0$
#550
b10011110 4
1#
b100111100 5
1$
#560
0$
#570
b1001111 4
1#
b10011110 5
1$
#580
0$
#590
b100111 4
1#
b1001111 5
1$
#600
0$
#610
b10011 4
1#
b100111 5
1$
#620
0$
#630
b1001 4
1#
b10011 5
1$
#640
0$
#650
b100 4
1#
b1001 5
1$
#660
0$
#670
b10 4
1#
b100 5
1$
#680
0$
#690
b1 4
1#
b10 5
1$
#700
0$
#710
b0 4
1#
b1 5
1$
#720
0$
#730
b1 ,
b10 .
1#
b0 5
1$
#740
0$
#750
b11 .
1#
b1 !
b1 )
b1 -
b10 /
1$
#760
0$
#770
b0 .
1"
1#
b11 /
1$
#780
0$
#790
0#
0"
b0 /
1$
